odoo/addons/hr_payroll_period/README.rst
odoo/addons/hr_payroll_period/__init__.py
odoo/addons/hr_payroll_period/__manifest__.py
odoo/addons/hr_payroll_period/data/date_range_type.xml
odoo/addons/hr_payroll_period/data/ir_cron.xml
odoo/addons/hr_payroll_period/data/ir_sequence_data.xml
odoo/addons/hr_payroll_period/i18n/de.po
odoo/addons/hr_payroll_period/i18n/es.po
odoo/addons/hr_payroll_period/i18n/es_AR.po
odoo/addons/hr_payroll_period/i18n/fr.po
odoo/addons/hr_payroll_period/i18n/hr_payroll_period.pot
odoo/addons/hr_payroll_period/i18n/hr_period.pot
odoo/addons/hr_payroll_period/i18n/it.po
odoo/addons/hr_payroll_period/i18n/pt.po
odoo/addons/hr_payroll_period/models/__init__.py
odoo/addons/hr_payroll_period/models/date_range_type.py
odoo/addons/hr_payroll_period/models/hr_contract.py
odoo/addons/hr_payroll_period/models/hr_employee.py
odoo/addons/hr_payroll_period/models/hr_fiscal_year.py
odoo/addons/hr_payroll_period/models/hr_payslip.py
odoo/addons/hr_payroll_period/models/hr_payslip_employees.py
odoo/addons/hr_payroll_period/models/hr_payslip_run.py
odoo/addons/hr_payroll_period/models/hr_period.py
odoo/addons/hr_payroll_period/readme/CONFIGURE.rst
odoo/addons/hr_payroll_period/readme/CONTRIBUTORS.rst
odoo/addons/hr_payroll_period/readme/DESCRIPTION.rst
odoo/addons/hr_payroll_period/readme/INSTALL.rst
odoo/addons/hr_payroll_period/readme/ROADMAP.rst
odoo/addons/hr_payroll_period/readme/USAGE.rst
odoo/addons/hr_payroll_period/security/hr_period_security.xml
odoo/addons/hr_payroll_period/security/ir.model.access.csv
odoo/addons/hr_payroll_period/static/description/icon.png
odoo/addons/hr_payroll_period/static/description/index.html
odoo/addons/hr_payroll_period/tests/__init__.py
odoo/addons/hr_payroll_period/tests/test_hr_fiscalyear.py
odoo/addons/hr_payroll_period/tests/test_payslip.py
odoo/addons/hr_payroll_period/views/date_range_type_view.xml
odoo/addons/hr_payroll_period/views/hr_fiscalyear_view.xml
odoo_addon_hr_payroll_period-16.0.1.1.0.dist-info/METADATA
odoo_addon_hr_payroll_period-16.0.1.1.0.dist-info/WHEEL
odoo_addon_hr_payroll_period-16.0.1.1.0.dist-info/top_level.txt
odoo_addon_hr_payroll_period-16.0.1.1.0.dist-info/RECORD
