Metadata-Version: 2.1
Name: odoo-addon-hr_payroll_period
Version: 16.0.1.1.0
Summary: Add payroll periods
Home-page: https://github.com/OCA/payroll
Author: Savoir-faire Linux, Odoo Community Association (OCA)
Author-email: support@odoo-community.org
License: AGPL-3
Classifier: Programming Language :: Python
Classifier: Framework :: Odoo
Classifier: Framework :: Odoo :: 16.0
Classifier: License :: OSI Approved :: GNU Affero General Public License v3
Requires-Python: >=3.10
Requires-Dist: odoo-addon-date-range<16.1dev,>=16.0dev
Requires-Dist: odoo-addon-payroll<16.1dev,>=16.0dev
Requires-Dist: odoo<16.1dev,>=16.0a
